nonebot_plugin_pcrjjc/__init__.py
nonebot_plugin_pcrjjc/aiorequests.py
nonebot_plugin_pcrjjc/bsgamesdk.py
nonebot_plugin_pcrjjc/config.py
nonebot_plugin_pcrjjc/main.py
nonebot_plugin_pcrjjc/pcrclient.py
nonebot_plugin_pcrjjc/query.py
nonebot_plugin_pcrjjc/rsacr.py
nonebot_plugin_pcrjjc/text2img.py
nonebot_plugin_pcrjjc-0.8.1.dist-info/LICENSE
nonebot_plugin_pcrjjc-0.8.1.dist-info/METADATA
nonebot_plugin_pcrjjc-0.8.1.dist-info/WHEEL
nonebot_plugin_pcrjjc-0.8.1.dist-info/top_level.txt
nonebot_plugin_pcrjjc-0.8.1.dist-info/RECORD
