Metadata-Version: 2.1
Name: nonebot-plugin-pcrjjc
Version: 0.8.1
Summary: pcrjjc排名监测插件
Author-email: reine-ishyanami <2402979195@qq.com>
License: AGPL-3
Project-URL: Homepage, https://github.com/reine-ishyanami/nonebot-plugin-pcrjjc
Project-URL: Bug Tracker, https://github.com/reine-ishyanami/nonebot-plugin-pcrjjc/issues
Classifier: Framework :: Pydantic
Classifier: License :: OSI Approved :: GNU Affero General Public License v3
Classifier: Programming Language :: Python :: 3
Classifier: Programming Language :: Python :: 3 :: Only
Classifier: Programming Language :: Python :: 3.10
Classifier: Programming Language :: Python :: 3.11
Classifier: Natural Language :: Chinese (Simplified)
Requires-Python: <4.0,>=3.10
License-File: LICENSE
Requires-Dist: msgpack >=1.0.5
Requires-Dist: requests >=2.30.0
Requires-Dist: Pillow >=9.5.0
Requires-Dist: pydantic >=1.10.14
Requires-Dist: python-dateutil >=2.8.2
Requires-Dist: pycryptodome >=3.18.0
Requires-Dist: nonebot2 >=2.0.0
Requires-Dist: nonebot-adapter-onebot >=2.2.3
Requires-Dist: nonebot-plugin-apscheduler >=0.3.0
